TansuoEs2016YuEs2017/README.md
TansuoEs2016YuEs2017/__init__.py
TansuoEs2016YuEs2017/__main__.py
TansuoEs2016YuEs2017/file.epub
TansuoEs2016YuEs2017/index.html
TansuoEs2016YuEs2017/css/__init__.py
TansuoEs2016YuEs2017/css/annotations.css
TansuoEs2016YuEs2017/css/main.css
TansuoEs2016YuEs2017/css/normalize.css
TansuoEs2016YuEs2017/css/popup.css
TansuoEs2016YuEs2017/font/__init__.py
TansuoEs2016YuEs2017/font/fontello.eot
TansuoEs2016YuEs2017/font/fontello.svg
TansuoEs2016YuEs2017/font/fontello.ttf
TansuoEs2016YuEs2017/font/fontello.woff
TansuoEs2016YuEs2017/img/__init__.py
TansuoEs2016YuEs2017/img/annotator-glyph-sprite.png
TansuoEs2016YuEs2017/img/annotator-icon-sprite.png
TansuoEs2016YuEs2017/img/apple-touch-icon.png
TansuoEs2016YuEs2017/img/cancelfullscreen.png
TansuoEs2016YuEs2017/img/close.png
TansuoEs2016YuEs2017/img/fullscreen.png
TansuoEs2016YuEs2017/img/loader.gif
TansuoEs2016YuEs2017/img/menu-icon.png
TansuoEs2016YuEs2017/img/save.png
TansuoEs2016YuEs2017/img/saved.png
TansuoEs2016YuEs2017/img/settings-s.png
TansuoEs2016YuEs2017/img/settings.png
TansuoEs2016YuEs2017/img/star.png
TansuoEs2016YuEs2017/js/__init__.py
TansuoEs2016YuEs2017/js/epub.js
TansuoEs2016YuEs2017/js/epub.min.js
TansuoEs2016YuEs2017/js/epub.min.map
TansuoEs2016YuEs2017/js/hooks.min.js
TansuoEs2016YuEs2017/js/hooks.min.map
TansuoEs2016YuEs2017/js/reader.js
TansuoEs2016YuEs2017/js/reader.js.map
TansuoEs2016YuEs2017/js/reader.min.js
TansuoEs2016YuEs2017/js/reader.min.map
TansuoEs2016YuEs2017/js/hooks/__init__.py
TansuoEs2016YuEs2017/js/hooks/extensions/__init__.py
TansuoEs2016YuEs2017/js/hooks/extensions/highlight.js
TansuoEs2016YuEs2017/js/libs/__init__.py
TansuoEs2016YuEs2017/js/libs/jquery.min.js
TansuoEs2016YuEs2017/js/libs/localforage.min.js
TansuoEs2016YuEs2017/js/libs/screenfull.js
TansuoEs2016YuEs2017/js/libs/screenfull.min.js
TansuoEs2016YuEs2017/js/libs/zip.min.js
TansuoEs2016YuEs2017/js/plugins/__init__.py
TansuoEs2016YuEs2017/js/plugins/hypothesis.js
tansuo_es2016_yu_es2017-2024.3.2.0.dist-info/METADATA
tansuo_es2016_yu_es2017-2024.3.2.0.dist-info/WHEEL
tansuo_es2016_yu_es2017-2024.3.2.0.dist-info/entry_points.txt
tansuo_es2016_yu_es2017-2024.3.2.0.dist-info/top_level.txt
tansuo_es2016_yu_es2017-2024.3.2.0.dist-info/RECORD
